{
  "aisha": { "sport": "taekwondo", "rating": 5 },
  "saja": { "sport": "football", "rating": 5 },
  "jamal": { "sport": "cardio", "rating": 5 },
  "zahran": { "sport": "football", "rating": 5 },
  "muneer": { "sport": "tennis", "rating": 5 },
  "noora": { "sport": "cycling", "rating": 5 },
  "rafik": { "sport": "running", "rating": 5 },
  "manzoor": { "sport": "swimming", "rating": 5 },
  "yaaseen": { "sport": "basketball", "rating": 5 },
  "taariq": { "sport": "football", "rating": 5 },
  "muhaimin": { "sport": "soccer", "rating": 5 },
  "adeeb": { "sport": "boxing", "rating": 5 },
  "kaleem": { "sport": "hiking", "rating": 5 },
  "jasmin": { "sport": "swimming", "rating": 5 },
  "maaz": { "sport": "weight", "rating": 5 },
  "nasir": { "sport": "basketball", "rating": 5 },
  "reyaz": { "sport": "soccer", "rating": 5 },
  "naadir": { "sport": "cycling", "rating": 5 },
  "isha": { "sport": "swimming", "rating": 5 },
  "thasneem": { "sport": "swimming", "rating": 5 },
  "shaheed": { "sport": "boxing", "rating": 5 },
  "alex": { "sport": "swimming", "rating": 4 },
  "johnny": { "sport": "basketball", "rating": 4 },
  "shaan": { "sport": "weight", "rating": 4 },
  "adam": { "sport": "taekwondo", "rating": 4 },
  "rishan": { "sport": "volleyball", "rating": 4 },
  "farish": { "sport": "badminton", "rating": 4 },
  "ayesha": { "sport": "gymnastics", "rating": 4 },
  "nashit": { "sport": "basketball", "rating": 4 },
  "shifa": { "sport": "climbing", "rating": 4 },
  "ahmed ali": { "sport": "weight", "rating": 4 },
  "munira": { "sport": "swimming", "rating": 4 },
  "khaled": { "sport": "football", "rating": 4 },
  "ishaq": { "sport": "taekwondo", "rating": 4 },
  "arif": { "sport": "climbing", "rating": 4 },
  "sameer": { "sport": "swimming", "rating": 4 },
  "fariha": { "sport": "cardio", "rating": 4 },
  "raeesa": { "sport": "badminton", "rating": 4 },
  "rizan": { "sport": "soccer", "rating": 4 },
  "faris": { "sport": "surfing", "rating": 4 },
  "raashid": { "sport": "running", "rating": 4 },
  "nimra": { "sport": "hiking", "rating": 4 },
  "mhmd": { "sport": "swimming", "rating": 3 },
  "shatha": { "sport": "basketball", "rating": 3 },
  "saeed": { "sport": "surfing", "rating": 3 },
  "shariq": { "sport": "boxing", "rating": 3 },
  "fathimath": { "sport": "swimming", "rating": 3 },
  "rizwan": { "sport": "soccer", "rating": 3 },
  "meher": { "sport": "sailing", "rating": 3 },
  "heba": { "sport": "yoga", "rating": 3 },
  "amna": { "sport": "gymnastics", "rating": 3 },
  "mohamed": { "sport": "yoga", "rating": 3 },
  "zainab": { "sport": "basketball", "rating": 3 },
  "amina": { "sport": "volleyball", "rating": 3 },
  "farhana": { "sport": "swimming", "rating": 3 },
  "hanan": { "sport": "cardio", "rating": 3 },
  "fahmi": { "sport": "boxing", "rating": 3 },
  "ruwaida": { "sport": "tennis", "rating": 3 },
  "yasha": { "sport": "swimming", "rating": 2 },
  "masha": { "sport": "swimming", "rating": 2 },
  "nasheed": { "sport": "yoga", "rating": 2 },
  "mahamud": { "sport": "cardio", "rating": 2 },
  "ayman": { "sport": "tennis", "rating": 2 },
  "razan": { "sport": "hiking", "rating": 4 },
  "salman": { "sport": "badminton", "rating": 2 },
  "sarrah": { "sport": "volleyball", "rating": 2 },
  "rayhan": { "sport": "cycling", "rating": 2 },
  "hamza": { "sport": "weight", "rating": 2 },
  "ibrahim": { "sport": "sailing", "rating": 2 },
  "shaakir": { "sport": "gymnastics", "rating": 2 },
  "sameera": { "sport": "yoga", "rating": 2 },
  "shail": { "sport": "football", "rating": 1 },
  "ahmed": { "sport": "cardio", "rating": 1 },
  "basha": { "sport": "surfing", "rating": 1 },
  "mishal": { "sport": "running", "rating": 1 },
  "najwa": { "sport": "volleyball", "rating": 1 }
}